pyHamiltonPSD
