Metadata-Version: 1.1
Name: pyHamiltonPSD
Version: 1.0.2
Summary: Basic Hamilton CE PSD Application
Home-page: UNKNOWN
Author: Hamilton CE - developed by Camil Milos
Author-email: contact.hce.ro@hamilton-ce.com
License: MIT
Keywords: Hamilton PSD
Platform: UNKNOWN
Classifier: Development Status :: 5 - Production/Stable
Classifier: Intended Audience :: Education
Classifier: Operating System :: Microsoft :: Windows :: Windows 10
Classifier: License :: OSI Approved :: MIT License
Classifier: Programming Language :: Python :: 3
